{
	"info": {
		"_postman_id": "7b086777-553a-4a64-8681-9c97ce5c2494",
		"name": "GameAPI examples",
		"schema": "https://schema.getpostman.com/json/collection/v2.1.0/collection.json",
		"_exporter_id": "2221047"
	},
	"item": [
		{
			"name": "GET game",
			"request": {
				"method": "GET",
				"header": [],
				"url": {
					"raw": "http://127.0.0.1:3000/game/2",
					"protocol": "http",
					"host": [
						"127",
						"0",
						"0",
						"1"
					],
					"port": "3000",
					"path": [
						"game",
						"2"
					]
				}
			},
			"response": []
		},
		{
			"name": "POST old game",
			"request": {
				"method": "POST",
				"header": [],
				"body": {
					"mode": "raw",
					"raw": "{\n    \"title\": \"Old game to DELETE\",\n    \"price\": 12743,\n    \"tags\": \"old, discount\",\n    \"publisher\": 3,\n    \"releaseDate\": \"2019-02-16 14:14:14\"\n}",
					"options": {
						"raw": {
							"language": "json"
						}
					}
				},
				"url": {
					"raw": "http://127.0.0.1:3000/game",
					"protocol": "http",
					"host": [
						"127",
						"0",
						"0",
						"1"
					],
					"port": "3000",
					"path": [
						"game"
					]
				}
			},
			"response": []
		},
		{
			"name": "POST recent game",
			"request": {
				"method": "POST",
				"header": [],
				"body": {
					"mode": "raw",
					"raw": "{\n    \"title\": \"Very real game\",\n    \"price\": 1743,\n    \"tags\": \"very, real\",\n    \"publisher\": 3,\n    \"releaseDate\": \"2022-05-16 14:14:14\"\n}",
					"options": {
						"raw": {
							"language": "json"
						}
					}
				},
				"url": {
					"raw": "http://127.0.0.1:3000/game",
					"protocol": "http",
					"host": [
						"127",
						"0",
						"0",
						"1"
					],
					"port": "3000",
					"path": [
						"game"
					]
				}
			},
			"response": []
		},
		{
			"name": "POST not-so-recent game",
			"request": {
				"method": "POST",
				"header": [],
				"body": {
					"mode": "raw",
					"raw": "{\n    \"title\": \"Very real game\",\n    \"price\": 1743,\n    \"tags\": \"very, real\",\n    \"publisher\": 3,\n    \"releaseDate\": \"2021-05-16 14:14:14\"\n}",
					"options": {
						"raw": {
							"language": "json"
						}
					}
				},
				"url": {
					"raw": "http://127.0.0.1:3000/game",
					"protocol": "http",
					"host": [
						"127",
						"0",
						"0",
						"1"
					],
					"port": "3000",
					"path": [
						"game"
					]
				}
			},
			"response": []
		},
		{
			"name": "PUT game",
			"request": {
				"method": "PUT",
				"header": [],
				"body": {
					"mode": "raw",
					"raw": "{\n    \"price\": 4001\n}",
					"options": {
						"raw": {
							"language": "json"
						}
					}
				},
				"url": {
					"raw": "http://127.0.0.1:3000/game/3",
					"protocol": "http",
					"host": [
						"127",
						"0",
						"0",
						"1"
					],
					"port": "3000",
					"path": [
						"game",
						"3"
					]
				}
			},
			"response": []
		},
		{
			"name": "DELETE game",
			"request": {
				"method": "DELETE",
				"header": [],
				"body": {
					"mode": "raw",
					"raw": "{\n    \"price\": 2000\n}",
					"options": {
						"raw": {
							"language": "json"
						}
					}
				},
				"url": {
					"raw": "http://127.0.0.1:3000/game/8",
					"protocol": "http",
					"host": [
						"127",
						"0",
						"0",
						"1"
					],
					"port": "3000",
					"path": [
						"game",
						"8"
					]
				}
			},
			"response": []
		},
		{
			"name": "GET game publisher",
			"request": {
				"method": "GET",
				"header": [],
				"url": {
					"raw": "http://127.0.0.1:3000/game/45/publisher",
					"protocol": "http",
					"host": [
						"127",
						"0",
						"0",
						"1"
					],
					"port": "3000",
					"path": [
						"game",
						"45",
						"publisher"
					]
				}
			},
			"response": []
		},
		{
			"name": "POST retire games",
			"request": {
				"method": "POST",
				"header": [],
				"url": {
					"raw": "http://127.0.0.1:3000/game/retire",
					"protocol": "http",
					"host": [
						"127",
						"0",
						"0",
						"1"
					],
					"port": "3000",
					"path": [
						"game",
						"retire"
					]
				}
			},
			"response": []
		}
	]
}